CREDITS
HISTORY.rst
LICENSE
MANIFEST.in
Makefile
README.rst
make.bat
setup.py
demo/anti_flood_ftpd.py
demo/basic_ftpd.py
demo/keycert.pem
demo/md5_ftpd.py
demo/multi_proc_ftp.py
demo/multi_thread_ftp.py
demo/throttled_ftpd.py
demo/tls_ftpd.py
demo/unix_daemon.py
demo/unix_ftpd.py
demo/winnt_ftpd.py
pyftpdlib/__init__.py
pyftpdlib/__main__.py
pyftpdlib/_compat.py
pyftpdlib/authorizers.py
pyftpdlib/filesystems.py
pyftpdlib/handlers.py
pyftpdlib/ioloop.py
pyftpdlib/log.py
pyftpdlib/servers.py
pyftpdlib_ustcblog.egg-info/PKG-INFO
pyftpdlib_ustcblog.egg-info/SOURCES.txt
pyftpdlib_ustcblog.egg-info/dependency_links.txt
pyftpdlib_ustcblog.egg-info/requires.txt
pyftpdlib_ustcblog.egg-info/top_level.txt
test/bench.py
test/keycert.pem
test/test_contrib.py
test/test_ftpd.py