Metadata-Version: 1.1
Name: pyftpdlib-ustcblog
Version: 1.4.1
Summary: USTC Blog fork of Very fast asynchronous FTP server library
Home-page: https://git.ustclug.org/ustc-blog/pyftpdlib
Author: Bojie Li
Author-email: bojieli@gmail.com
License: MIT
Keywords: ustc,blog,ftp,ftps,server,ftpd,daemon,python,ssl,sendfile,asynchronous,nonblocking,eventdriven,rfc959,rfc1123,rfc2228,rfc2428,rfc2640,rfc3659
Platform: Platform Independent
Classifier: Development Status :: 5 - Production/Stable
Classifier: Environment :: Console
Classifier: Intended Audience :: Developers
Classifier: Intended Audience :: System Administrators
Classifier: License :: OSI Approved :: MIT License
Classifier: Operating System :: OS Independent
Classifier: Programming Language :: Python
Classifier: Topic :: Internet :: File Transfer Protocol (FTP)
Classifier: Topic :: Software Development :: Libraries :: Python Modules
Classifier: Topic :: System :: Filesystems
Classifier: Programming Language :: Python
Classifier: Programming Language :: Python :: 2
Classifier: Programming Language :: Python :: 2.4
Classifier: Programming Language :: Python :: 2.5
Classifier: Programming Language :: Python :: 2.6
Classifier: Programming Language :: Python :: 2.7
Classifier: Programming Language :: Python :: 3
Classifier: Programming Language :: Python :: 3.0
Classifier: Programming Language :: Python :: 3.1
Classifier: Programming Language :: Python :: 3.2
Classifier: Programming Language :: Python :: 3.3
Classifier: Programming Language :: Python :: 3.4
